pathcache/__init__.py
pathcache/pathcache.py
pathcache-0.0.5.20231206134700.dist-info/LICENSE.txt
pathcache-0.0.5.20231206134700.dist-info/METADATA
pathcache-0.0.5.20231206134700.dist-info/WHEEL
pathcache-0.0.5.20231206134700.dist-info/top_level.txt
pathcache-0.0.5.20231206134700.dist-info/RECORD
