Metadata-Version: 2.1
Name: pathcache
Version: 0.0.5.20231206134700
Summary: Cache file using path
Home-page: https://github.com/LiXiaYu/pathcache
Author: LiXiaYu
Author-email: aasll@126.com
Classifier: Programming Language :: Python :: 3
Classifier: License :: OSI Approved :: MIT License
Classifier: Operating System :: OS Independent
Requires-Python: >=3.6
License-File: LICENSE.txt
